calculin/__init__.py
calculin/operacion.py
calculin-0.0.5.dist-info/LICENSE
calculin-0.0.5.dist-info/METADATA
calculin-0.0.5.dist-info/WHEEL
calculin-0.0.5.dist-info/top_level.txt
calculin-0.0.5.dist-info/RECORD
