Metadata-Version: 2.1
Name: calculin
Version: 0.0.5
License-File: LICENSE
